fext/__init__.py
fext/eheapq.cpython-38-x86_64-linux-gnu.so
fext-0.2.0.dist-info/top_level.txt
fext-0.2.0.dist-info/METADATA
fext-0.2.0.dist-info/RECORD
fext-0.2.0.dist-info/LICENSE
fext-0.2.0.dist-info/WHEEL
