Metadata-Version: 2.1
Name: fext
Version: 0.2.0
Summary: Extensions to standard Python's heapq for performance applications
Home-page: https://github.com/thoth-station/fext
Author: Fridolin Pokorny
Author-email: fridolin@redhat.com
License: GPLv3+
Download-URL: https://pypi.org/project/fext
Platform: UNKNOWN
